turbo_stream/__init__.py
turbo_stream/google_analyitcs/__init__.py
turbo_stream/google_analyitcs/reader.py
turbo_stream/google_search_console/__init__.py
turbo_stream/google_search_console/reader.py
turbo_stream/onesignal/__init__.py
turbo_stream/onesignal/reader.py
turbo_stream/utils/__init__.py
turbo_stream/utils/aws_handlers.py
turbo_stream/utils/date_handlers.py
turbo_stream/utils/file_handlers.py
turbo_stream/utils/request_handlers.py
turbo_stream-0.0.8.dist-info/LICENSE
turbo_stream-0.0.8.dist-info/METADATA
turbo_stream-0.0.8.dist-info/WHEEL
turbo_stream-0.0.8.dist-info/top_level.txt
turbo_stream-0.0.8.dist-info/RECORD
